event_stream.cpython-311-x86_64-linux-musl.so
event_stream-1.6.3.dist-info/LICENSE
event_stream-1.6.3.dist-info/WHEEL
event_stream-1.6.3.dist-info/top_level.txt
event_stream-1.6.3.dist-info/RECORD
event_stream-1.6.3.dist-info/METADATA
event_stream.libs/libgcc_s-a3a07607.so.1
event_stream.libs/libstdc++-496613c0.so.6.0.32
