Metadata-Version: 2.1
Name: event_stream
Version: 1.6.3
Summary: Read and write Event Stream (.es) files
Home-page: https://github.com/neuromorphicsystems/event_stream
Author: Alexandre Marcireau
Author-email: alexandre.marcireau@gmail.com
Classifier: Programming Language :: Python :: 3
Classifier: License :: OSI Approved :: GNU General Public License v3 (GPLv3)
Classifier: Operating System :: OS Independent
License-File: LICENSE
Requires-Dist: numpy >=1.24
